CHANGES.txt
LICENSE.txt
MANIFEST.in
README.md
requirements.txt
setup.cfg
setup.py
Tavi.egg-info/PKG-INFO
Tavi.egg-info/SOURCES.txt
Tavi.egg-info/dependency_links.txt
Tavi.egg-info/not-zip-safe
Tavi.egg-info/requires.txt
Tavi.egg-info/top_level.txt
tavi/__init__.py
tavi/commands.py
tavi/documents.py
tavi/errors.py
tavi/fields.py
tavi/base/__init__.py
tavi/base/documents.py
tavi/base/fields.py
tavi/utils/__init__.py
tavi/utils/timer.py