Metadata-Version: 1.0
Name: Tavi
Version: 1.4.1
Summary: Super thin Mongo object mapper for Python.
Home-page: https://github.com/bnadlerjr/tavi
Author: Bob Nadler Jr.
Author-email: bnadlerjr@gmail.com
License: LICENSE.txt
Platform: UNKNOWN
